{
    "101": {
        "id": 101,
        "FIINGPLAAEB": "GreaterOrEqual",
        "materialId": 410004,
        "EIEJJGNNBIL": 1
    },
    "102": {
        "id": 102,
        "FIINGPLAAEB": "GreaterOrEqual",
        "materialId": 410005,
        "EIEJJGNNBIL": 1
    },
    "103": {
        "id": 103,
        "FIINGPLAAEB": "GreaterOrEqual",
        "materialId": 410006,
        "EIEJJGNNBIL": 1
    },
    "104": {
        "id": 104,
        "FIINGPLAAEB": "GreaterOrEqual",
        "materialId": 410007,
        "EIEJJGNNBIL": 1
    },
    "105": {
        "id": 105,
        "FIINGPLAAEB": "GreaterOrEqual",
        "materialId": 410008,
        "EIEJJGNNBIL": 1
    },
    "106": {
        "id": 106,
        "FIINGPLAAEB": "GreaterOrEqual",
        "materialId": 410009,
        "EIEJJGNNBIL": 1
    },
    "107": {
        "id": 107,
        "FIINGPLAAEB": "GreaterOrEqual",
        "materialId": 410001,
        "EIEJJGNNBIL": 1
    },
    "108": {
        "id": 108,
        "FIINGPLAAEB": "GreaterOrEqual",
        "materialId": 410002,
        "EIEJJGNNBIL": 1
    },
    "109": {
        "id": 109,
        "FIINGPLAAEB": "GreaterOrEqual",
        "materialId": 410003,
        "EIEJJGNNBIL": 1
    }
}